financial_report/__init__.py
financial_report/main.py
financial_report/report.py
financial_report_by_podpivas-0.1.0.dist-info/METADATA
financial_report_by_podpivas-0.1.0.dist-info/WHEEL
financial_report_by_podpivas-0.1.0.dist-info/entry_points.txt
financial_report_by_podpivas-0.1.0.dist-info/top_level.txt
financial_report_by_podpivas-0.1.0.dist-info/RECORD
